e3nn_jax/__init__.py
e3nn_jax/equinox.py
e3nn_jax/flax.py
e3nn_jax/haiku.py
e3nn_jax/legacy.py
e3nn_jax/perm.py
e3nn_jax/utils.py
e3nn_jax/_src/J.py
e3nn_jax/_src/__init__.py
e3nn_jax/_src/activation.py
e3nn_jax/_src/basic.py
e3nn_jax/_src/config.py
e3nn_jax/_src/dropout_haiku.py
e3nn_jax/_src/fc_tp_haiku.py
e3nn_jax/_src/gate.py
e3nn_jax/_src/grad.py
e3nn_jax/_src/irreps.py
e3nn_jax/_src/irreps_array.py
e3nn_jax/_src/linear.py
e3nn_jax/_src/linear_equinox.py
e3nn_jax/_src/linear_flax.py
e3nn_jax/_src/linear_haiku.py
e3nn_jax/_src/mlp_flax.py
e3nn_jax/_src/mlp_haiku.py
e3nn_jax/_src/radial.py
e3nn_jax/_src/radius_graph.py
e3nn_jax/_src/reduced_tensor_product.py
e3nn_jax/_src/rotation.py
e3nn_jax/_src/s2grid.py
e3nn_jax/_src/scatter.py
e3nn_jax/_src/so3.py
e3nn_jax/_src/su2.py
e3nn_jax/_src/symmetric_tensor_product_haiku.py
e3nn_jax/_src/tensor_product_with_spherical_harmonics.py
e3nn_jax/_src/tensor_products.py
e3nn_jax/_src/batchnorm/__init__.py
e3nn_jax/_src/batchnorm/bn.py
e3nn_jax/_src/batchnorm/bn_flax.py
e3nn_jax/_src/batchnorm/bn_haiku.py
e3nn_jax/_src/legacy/__init__.py
e3nn_jax/_src/legacy/core_tensor_product.py
e3nn_jax/_src/legacy/functional_fully_connected_tensor_product.py
e3nn_jax/_src/spherical_harmonics/__init__.py
e3nn_jax/_src/spherical_harmonics/legendre.py
e3nn_jax/_src/spherical_harmonics/recursive.py
e3nn_jax/_src/utils/__init__.py
e3nn_jax/_src/utils/decorators.py
e3nn_jax/_src/utils/dtype.py
e3nn_jax/_src/utils/einsum.py
e3nn_jax/_src/utils/jit.py
e3nn_jax/_src/utils/math_numpy.py
e3nn_jax/_src/utils/optimize_jaxpr.py
e3nn_jax/_src/utils/sum_tensors.py
e3nn_jax/_src/utils/sympy.py
e3nn_jax/_src/utils/test.py
e3nn_jax/_src/utils/vmap.py
e3nn_jax/experimental/__init__.py
e3nn_jax/experimental/linear_shtp.py
e3nn_jax/experimental/point_convolution.py
e3nn_jax/experimental/transformer.py
e3nn_jax/experimental/voxel_convolution.py
e3nn_jax/experimental/voxel_pooling.py
e3nn_jax/irrep/__init__.py
tests/conftest.py
tests/noxfile.py
e3nn_jax-0.20.7.dist-info/LICENSE
e3nn_jax-0.20.7.dist-info/METADATA
e3nn_jax-0.20.7.dist-info/WHEEL
e3nn_jax-0.20.7.dist-info/top_level.txt
e3nn_jax-0.20.7.dist-info/RECORD
