Metadata-Version: 2.1
Name: e3nn-jax
Version: 0.20.7
Summary: Equivariant convolutional neural networks for the group E(3) of 3 dimensional rotations, translations, and mirrors.
Author-email: e3nn team <geiger.mario@gmail.com>
License: Apache License
Project-URL: homepage, https://e3nn-jax.readthedocs.io
Project-URL: documentation, https://e3nn-jax.readthedocs.io
Project-URL: repository, https://github.com/e3nn/e3nn-jax
Project-URL: changelog, https://github.com/e3nn/e3nn-jax/blob/main/CHANGELOG.md
Classifier: Programming Language :: Python :: 3.9
Classifier: Programming Language :: Python :: 3.10
Classifier: Programming Language :: Python :: 3.11
Requires-Python: >=3.9
License-File: LICENSE
Requires-Dist: jax
Requires-Dist: jaxlib
Requires-Dist: sympy
Requires-Dist: numpy
Requires-Dist: attrs
Provides-Extra: dev
Requires-Dist: plotly ; extra == 'dev'
Requires-Dist: kaleido ; extra == 'dev'
Requires-Dist: jraph ; extra == 'dev'
Requires-Dist: flax ; extra == 'dev'
Requires-Dist: dm-haiku ; extra == 'dev'
Requires-Dist: equinox ; extra == 'dev'
Requires-Dist: optax ; extra == 'dev'
Requires-Dist: tqdm ; extra == 'dev'
Requires-Dist: pytest ; extra == 'dev'
Requires-Dist: nox ; extra == 'dev'
Requires-Dist: s2fft ; extra == 'dev'
